gdbplotter/__init__.py
gdbplotter/__main__.py
gdbplotter/gdbparser.py
gdbplotter/plotter_ui.py
gdbplotter-0.1.2.dist-info/WHEEL
gdbplotter-0.1.2.dist-info/entry_points.txt
gdbplotter-0.1.2.dist-info/METADATA
gdbplotter-0.1.2.dist-info/RECORD
