Metadata-Version: 2.3
Name: gdbplotter
Version: 0.1.2
Summary: Simple UI for printing GDB memory values
License: The MIT License (MIT)
Requires-Dist: matplotlib>=3.10.7
Requires-Dist: numpy>=2.3.5
Requires-Python: >=3.11
Project-URL: homepage, https://github.com/1atabey1/gdbplotter
Project-URL: repository, https://github.com/1atabey1/gdbplotter
